{
  "location": {
    "name": "Ahmedabad",
    "region": "Gujarat",
    "country": "India",
    "lat": 23.0333,
    "lon": 72.6167,
    "tz_id": "Asia/Kolkata",
    "localtime_epoch": 1781093431,
    "localtime": "2026-06-10 17:40"
  },
  "current": {
    "last_updated_epoch": 1781091900,
    "last_updated": "2026-06-10 17:15",
    "temp_c": 41.5,
    "temp_f": 106.7,
    "is_day": 1,
    "condition": {
      "text": "Sunny",
      "icon": "//cdn.weatherapi.com/weather/64x64/day/113.png",
      "code": 1000
    },
    "wind_mph": 14.3,
    "wind_kph": 23.0,
    "wind_degree": 238,
    "wind_dir": "WSW",
    "pressure_mb": 999.0,
    "pressure_in": 29.51,
    "precip_mm": 0.0,
    "precip_in": 0.0,
    "humidity": 23,
    "cloud": 4,
    "feelslike_c": 33.0,
    "feelslike_f": 91.4,
    "windchill_c": 41.5,
    "windchill_f": 106.8,
    "heatindex_c": 43.4,
    "heatindex_f": 110.1,
    "dewpoint_c": 16.0,
    "dewpoint_f": 60.8,
    "vis_km": 10.0,
    "vis_miles": 6.0,
    "uv": 1.2,
    "gust_mph": 16.5,
    "gust_kph": 26.5,
    "will_it_rain": 0,
    "chance_of_rain": 1,
    "will_it_snow": 0,
    "chance_of_snow": 0
  }
}