{
  "location": {
    "name": "Ahmedabad",
    "region": "Gujarat",
    "country": "India",
    "lat": 23.0333,
    "lon": 72.6167,
    "tz_id": "Asia/Kolkata",
    "localtime_epoch": 1775402414,
    "localtime": "2026-04-05 20:50"
  },
  "current": {
    "last_updated_epoch": 1775402100,
    "last_updated": "2026-04-05 20:45",
    "temp_c": 30.2,
    "temp_f": 86.4,
    "is_day": 0,
    "condition": {
      "text": "Overcast",
      "icon": "//cdn.weatherapi.com/weather/64x64/night/122.png",
      "code": 1009
    },
    "wind_mph": 10.7,
    "wind_kph": 17.3,
    "wind_degree": 307,
    "wind_dir": "NW",
    "pressure_mb": 1008.0,
    "pressure_in": 29.77,
    "precip_mm": 0.0,
    "precip_in": 0.0,
    "humidity": 25,
    "cloud": 50,
    "feelslike_c": 28.4,
    "feelslike_f": 83.1,
    "windchill_c": 29.6,
    "windchill_f": 85.3,
    "heatindex_c": 27.8,
    "heatindex_f": 82.0,
    "dewpoint_c": 6.7,
    "dewpoint_f": 44.0,
    "vis_km": 4.0,
    "vis_miles": 2.0,
    "uv": 0.0,
    "gust_mph": 17.9,
    "gust_kph": 28.8
  }
}