{
  "location": {
    "name": "Ahmedabad",
    "region": "Gujarat",
    "country": "India",
    "lat": 23.0333,
    "lon": 72.6167,
    "tz_id": "Asia/Kolkata",
    "localtime_epoch": 1772530111,
    "localtime": "2026-03-03 14:58"
  },
  "current": {
    "last_updated_epoch": 1772529300,
    "last_updated": "2026-03-03 14:45",
    "temp_c": 34.2,
    "temp_f": 93.6,
    "is_day": 1,
    "condition": {
      "text": "Overcast",
      "icon": "//cdn.weatherapi.com/weather/64x64/day/122.png",
      "code": 1009
    },
    "wind_mph": 6.7,
    "wind_kph": 10.8,
    "wind_degree": 266,
    "wind_dir": "W",
    "pressure_mb": 1011.0,
    "pressure_in": 29.85,
    "precip_mm": 0.0,
    "precip_in": 0.0,
    "humidity": 20,
    "cloud": 0,
    "feelslike_c": 32.2,
    "feelslike_f": 90.0,
    "windchill_c": 37.3,
    "windchill_f": 99.1,
    "heatindex_c": 36.1,
    "heatindex_f": 97.0,
    "dewpoint_c": 3.7,
    "dewpoint_f": 38.7,
    "vis_km": 5.0,
    "vis_miles": 3.0,
    "uv": 6.6,
    "gust_mph": 7.7,
    "gust_kph": 12.4
  }
}