{
  "location": {
    "name": "Ahmedabad",
    "region": "Gujarat",
    "country": "India",
    "lat": 23.0333,
    "lon": 72.6167,
    "tz_id": "Asia/Kolkata",
    "localtime_epoch": 1771417856,
    "localtime": "2026-02-18 18:00"
  },
  "current": {
    "last_updated_epoch": 1771417800,
    "last_updated": "2026-02-18 18:00",
    "temp_c": 30.4,
    "temp_f": 86.7,
    "is_day": 1,
    "condition": {
      "text": "Overcast",
      "icon": "//cdn.weatherapi.com/weather/64x64/day/122.png",
      "code": 1009
    },
    "wind_mph": 2.2,
    "wind_kph": 3.6,
    "wind_degree": 136,
    "wind_dir": "SE",
    "pressure_mb": 1009.0,
    "pressure_in": 29.8,
    "precip_mm": 0.0,
    "precip_in": 0.0,
    "humidity": 24,
    "cloud": 0,
    "feelslike_c": 28.3,
    "feelslike_f": 83.0,
    "windchill_c": 29.0,
    "windchill_f": 84.2,
    "heatindex_c": 27.0,
    "heatindex_f": 80.7,
    "dewpoint_c": 4.8,
    "dewpoint_f": 40.7,
    "vis_km": 4.0,
    "vis_miles": 2.0,
    "uv": 0.0,
    "gust_mph": 2.6,
    "gust_kph": 4.2
  }
}