{
  "location": {
    "name": "Bengaluru",
    "region": "Karnataka",
    "country": "India",
    "lat": 12.9833,
    "lon": 77.5833,
    "tz_id": "Asia/Kolkata",
    "localtime_epoch": 1764569775,
    "localtime": "2025-12-01 11:46"
  },
  "current": {
    "last_updated_epoch": 1764569700,
    "last_updated": "2025-12-01 11:45",
    "temp_c": 21.1,
    "temp_f": 70.0,
    "is_day": 1,
    "condition": {
      "text": "Partly cloudy",
      "icon": "//cdn.weatherapi.com/weather/64x64/day/116.png",
      "code": 1003
    },
    "wind_mph": 10.3,
    "wind_kph": 16.6,
    "wind_degree": 14,
    "wind_dir": "NNE",
    "pressure_mb": 1017.0,
    "pressure_in": 30.03,
    "precip_mm": 0.02,
    "precip_in": 0.0,
    "humidity": 83,
    "cloud": 75,
    "feelslike_c": 21.1,
    "feelslike_f": 70.0,
    "windchill_c": 23.4,
    "windchill_f": 74.2,
    "heatindex_c": 25.2,
    "heatindex_f": 77.4,
    "dewpoint_c": 17.3,
    "dewpoint_f": 63.2,
    "vis_km": 6.0,
    "vis_miles": 3.0,
    "uv": 7.3,
    "gust_mph": 11.8,
    "gust_kph": 19.0
  }
}