{
  "location": {
    "name": "Bengaluru",
    "region": "Karnataka",
    "country": "India",
    "lat": 12.9833,
    "lon": 77.5833,
    "tz_id": "Asia/Kolkata",
    "localtime_epoch": 1771310471,
    "localtime": "2026-02-17 12:11"
  },
  "current": {
    "last_updated_epoch": 1771309800,
    "last_updated": "2026-02-17 12:00",
    "temp_c": 25.3,
    "temp_f": 77.5,
    "is_day": 1,
    "condition": {
      "text": "Sunny",
      "icon": "//cdn.weatherapi.com/weather/64x64/day/113.png",
      "code": 1000
    },
    "wind_mph": 8.3,
    "wind_kph": 13.3,
    "wind_degree": 92,
    "wind_dir": "E",
    "pressure_mb": 1018.0,
    "pressure_in": 30.06,
    "precip_mm": 0.0,
    "precip_in": 0.0,
    "humidity": 41,
    "cloud": 0,
    "feelslike_c": 24.1,
    "feelslike_f": 75.4,
    "windchill_c": 28.2,
    "windchill_f": 82.7,
    "heatindex_c": 26.3,
    "heatindex_f": 79.3,
    "dewpoint_c": 3.9,
    "dewpoint_f": 39.1,
    "vis_km": 6.0,
    "vis_miles": 3.0,
    "uv": 11.6,
    "gust_mph": 9.5,
    "gust_kph": 15.3
  }
}