{
  "location": {
    "name": "Bengaluru",
    "region": "Karnataka",
    "country": "India",
    "lat": 12.9833,
    "lon": 77.5833,
    "tz_id": "Asia/Kolkata",
    "localtime_epoch": 1764981689,
    "localtime": "2025-12-06 06:11"
  },
  "current": {
    "last_updated_epoch": 1764981000,
    "last_updated": "2025-12-06 06:00",
    "temp_c": 18.2,
    "temp_f": 64.8,
    "is_day": 0,
    "condition": {
      "text": "Mist",
      "icon": "//cdn.weatherapi.com/weather/64x64/night/143.png",
      "code": 1030
    },
    "wind_mph": 6.5,
    "wind_kph": 10.4,
    "wind_degree": 72,
    "wind_dir": "ENE",
    "pressure_mb": 1019.0,
    "pressure_in": 30.09,
    "precip_mm": 0.0,
    "precip_in": 0.0,
    "humidity": 94,
    "cloud": 75,
    "feelslike_c": 18.2,
    "feelslike_f": 64.8,
    "windchill_c": 16.6,
    "windchill_f": 61.9,
    "heatindex_c": 16.6,
    "heatindex_f": 61.9,
    "dewpoint_c": 15.1,
    "dewpoint_f": 59.2,
    "vis_km": 2.0,
    "vis_miles": 1.0,
    "uv": 0.0,
    "gust_mph": 10.7,
    "gust_kph": 17.2
  }
}