{
  "location": {
    "name": "Bengaluru",
    "region": "Karnataka",
    "country": "India",
    "lat": 12.9833,
    "lon": 77.5833,
    "tz_id": "Asia/Kolkata",
    "localtime_epoch": 1769192144,
    "localtime": "2026-01-23 23:45"
  },
  "current": {
    "last_updated_epoch": 1769191200,
    "last_updated": "2026-01-23 23:30",
    "temp_c": 18.1,
    "temp_f": 64.6,
    "is_day": 0,
    "condition": {
      "text": "Mist",
      "icon": "//cdn.weatherapi.com/weather/64x64/night/143.png",
      "code": 1030
    },
    "wind_mph": 11.4,
    "wind_kph": 18.4,
    "wind_degree": 104,
    "wind_dir": "ESE",
    "pressure_mb": 1020.0,
    "pressure_in": 30.12,
    "precip_mm": 0.0,
    "precip_in": 0.0,
    "humidity": 88,
    "cloud": 25,
    "feelslike_c": 18.1,
    "feelslike_f": 64.6,
    "windchill_c": 17.7,
    "windchill_f": 63.8,
    "heatindex_c": 17.7,
    "heatindex_f": 63.8,
    "dewpoint_c": 15.2,
    "dewpoint_f": 59.3,
    "vis_km": 4.0,
    "vis_miles": 2.0,
    "uv": 0.0,
    "gust_mph": 18.9,
    "gust_kph": 30.5
  }
}