{
  "location": {
    "name": "Chennai",
    "region": "Tamil Nadu",
    "country": "India",
    "lat": 13.0833,
    "lon": 80.2833,
    "tz_id": "Asia/Kolkata",
    "localtime_epoch": 1777079376,
    "localtime": "2026-04-25 06:39"
  },
  "current": {
    "last_updated_epoch": 1777078800,
    "last_updated": "2026-04-25 06:30",
    "temp_c": 28.8,
    "temp_f": 83.9,
    "is_day": 1,
    "condition": {
      "text": "Sunny",
      "icon": "//cdn.weatherapi.com/weather/64x64/day/113.png",
      "code": 1000
    },
    "wind_mph": 12.1,
    "wind_kph": 19.4,
    "wind_degree": 191,
    "wind_dir": "SSW",
    "pressure_mb": 1008.0,
    "pressure_in": 29.78,
    "precip_mm": 0.0,
    "precip_in": 0.0,
    "humidity": 75,
    "cloud": 25,
    "feelslike_c": 33.2,
    "feelslike_f": 91.8,
    "windchill_c": 28.8,
    "windchill_f": 83.9,
    "heatindex_c": 33.2,
    "heatindex_f": 91.8,
    "dewpoint_c": 23.9,
    "dewpoint_f": 74.9,
    "vis_km": 10.0,
    "vis_miles": 6.0,
    "uv": 0.1,
    "gust_mph": 16.9,
    "gust_kph": 27.3
  }
}