{
  "location": {
    "name": "Chennai",
    "region": "Tamil Nadu",
    "country": "India",
    "lat": 13.0833,
    "lon": 80.2833,
    "tz_id": "Asia/Kolkata",
    "localtime_epoch": 1772499567,
    "localtime": "2026-03-03 06:29"
  },
  "current": {
    "last_updated_epoch": 1772498700,
    "last_updated": "2026-03-03 06:15",
    "temp_c": 23.3,
    "temp_f": 73.9,
    "is_day": 1,
    "condition": {
      "text": "Sunny",
      "icon": "//cdn.weatherapi.com/weather/64x64/day/113.png",
      "code": 1000
    },
    "wind_mph": 7.6,
    "wind_kph": 12.2,
    "wind_degree": 226,
    "wind_dir": "SW",
    "pressure_mb": 1011.0,
    "pressure_in": 29.85,
    "precip_mm": 0.0,
    "precip_in": 0.0,
    "humidity": 73,
    "cloud": 6,
    "feelslike_c": 25.2,
    "feelslike_f": 77.3,
    "windchill_c": 23.3,
    "windchill_f": 73.9,
    "heatindex_c": 25.2,
    "heatindex_f": 77.3,
    "dewpoint_c": 18.1,
    "dewpoint_f": 64.5,
    "vis_km": 10.0,
    "vis_miles": 6.0,
    "uv": 0.0,
    "gust_mph": 13.0,
    "gust_kph": 21.0
  }
}