{
  "location": {
    "name": "Delhi",
    "region": "Ontario",
    "country": "Canada",
    "lat": 42.85,
    "lon": -80.5,
    "tz_id": "America/Toronto",
    "localtime_epoch": 1784092721,
    "localtime": "2026-07-15 01:18"
  },
  "current": {
    "last_updated_epoch": 1784091600,
    "last_updated": "2026-07-15 01:00",
    "temp_c": 25.1,
    "temp_f": 77.2,
    "is_day": 0,
    "condition": {
      "text": "Clear",
      "icon": "//cdn.weatherapi.com/weather/64x64/night/113.png",
      "code": 1000
    },
    "wind_mph": 14.1,
    "wind_kph": 22.7,
    "wind_degree": 266,
    "wind_dir": "W",
    "pressure_mb": 1015.0,
    "pressure_in": 29.97,
    "precip_mm": 0.0,
    "precip_in": 0.0,
    "humidity": 87,
    "cloud": 0,
    "feelslike_c": 27.6,
    "feelslike_f": 81.7,
    "windchill_c": 24.7,
    "windchill_f": 76.5,
    "heatindex_c": 27.0,
    "heatindex_f": 80.6,
    "dewpoint_c": 22.1,
    "dewpoint_f": 71.9,
    "vis_km": 10.0,
    "vis_miles": 6.0,
    "uv": 0.0,
    "gust_mph": 28.2,
    "gust_kph": 45.3,
    "will_it_rain": 0,
    "chance_of_rain": 11,
    "will_it_snow": 0,
    "chance_of_snow": 0
  }
}