{
  "location": {
    "name": "Delhi",
    "region": "Ontario",
    "country": "Canada",
    "lat": 42.85,
    "lon": -80.5,
    "tz_id": "America/Toronto",
    "localtime_epoch": 1774182048,
    "localtime": "2026-03-22 08:20"
  },
  "current": {
    "last_updated_epoch": 1774181700,
    "last_updated": "2026-03-22 08:15",
    "temp_c": 1.6,
    "temp_f": 34.9,
    "is_day": 1,
    "condition": {
      "text": "Sunny",
      "icon": "//cdn.weatherapi.com/weather/64x64/day/113.png",
      "code": 1000
    },
    "wind_mph": 8.1,
    "wind_kph": 13.0,
    "wind_degree": 276,
    "wind_dir": "W",
    "pressure_mb": 1004.0,
    "pressure_in": 29.65,
    "precip_mm": 0.0,
    "precip_in": 0.0,
    "humidity": 94,
    "cloud": 0,
    "feelslike_c": -2.1,
    "feelslike_f": 28.3,
    "windchill_c": 1.5,
    "windchill_f": 34.7,
    "heatindex_c": 3.3,
    "heatindex_f": 37.9,
    "dewpoint_c": 1.1,
    "dewpoint_f": 34.0,
    "vis_km": 10.0,
    "vis_miles": 6.0,
    "uv": 0.1,
    "gust_mph": 16.9,
    "gust_kph": 27.2
  }
}