{
  "location": {
    "name": "Kolkata",
    "region": "West Bengal",
    "country": "India",
    "lat": 22.5697,
    "lon": 88.3697,
    "tz_id": "Asia/Kolkata",
    "localtime_epoch": 1767690909,
    "localtime": "2026-01-06 14:45"
  },
  "current": {
    "last_updated_epoch": 1767690900,
    "last_updated": "2026-01-06 14:45",
    "temp_c": 18.1,
    "temp_f": 64.6,
    "is_day": 1,
    "condition": {
      "text": "Mist",
      "icon": "//cdn.weatherapi.com/weather/64x64/day/143.png",
      "code": 1030
    },
    "wind_mph": 10.3,
    "wind_kph": 16.6,
    "wind_degree": 339,
    "wind_dir": "NNW",
    "pressure_mb": 1017.0,
    "pressure_in": 30.03,
    "precip_mm": 0.0,
    "precip_in": 0.0,
    "humidity": 64,
    "cloud": 50,
    "feelslike_c": 18.1,
    "feelslike_f": 64.6,
    "windchill_c": 24.9,
    "windchill_f": 76.9,
    "heatindex_c": 23.7,
    "heatindex_f": 74.7,
    "dewpoint_c": 0.0,
    "dewpoint_f": 32.1,
    "vis_km": 1.7,
    "vis_miles": 1.0,
    "uv": 2.1,
    "gust_mph": 11.8,
    "gust_kph": 19.0
  }
}