{
  "location": {
    "name": "Kolkata",
    "region": "West Bengal",
    "country": "India",
    "lat": 22.5697,
    "lon": 88.3697,
    "tz_id": "Asia/Kolkata",
    "localtime_epoch": 1766816022,
    "localtime": "2025-12-27 11:43"
  },
  "current": {
    "last_updated_epoch": 1766815200,
    "last_updated": "2025-12-27 11:30",
    "temp_c": 21.2,
    "temp_f": 70.2,
    "is_day": 1,
    "condition": {
      "text": "Mist",
      "icon": "//cdn.weatherapi.com/weather/64x64/day/143.png",
      "code": 1030
    },
    "wind_mph": 7.6,
    "wind_kph": 12.2,
    "wind_degree": 337,
    "wind_dir": "NNW",
    "pressure_mb": 1016.0,
    "pressure_in": 30.0,
    "precip_mm": 0.0,
    "precip_in": 0.0,
    "humidity": 60,
    "cloud": 0,
    "feelslike_c": 21.2,
    "feelslike_f": 70.2,
    "windchill_c": 23.0,
    "windchill_f": 73.3,
    "heatindex_c": 24.2,
    "heatindex_f": 75.5,
    "dewpoint_c": 7.5,
    "dewpoint_f": 45.5,
    "vis_km": 1.7,
    "vis_miles": 1.0,
    "uv": 5.2,
    "gust_mph": 8.7,
    "gust_kph": 14.1
  }
}