{
  "location": {
    "name": "Mumbai",
    "region": "Maharashtra",
    "country": "India",
    "lat": 18.975,
    "lon": 72.826,
    "tz_id": "Asia/Kolkata",
    "localtime_epoch": 1773868939,
    "localtime": "2026-03-19 02:52"
  },
  "current": {
    "last_updated_epoch": 1773868500,
    "last_updated": "2026-03-19 02:45",
    "temp_c": 26.3,
    "temp_f": 79.3,
    "is_day": 0,
    "condition": {
      "text": "Mist",
      "icon": "//cdn.weatherapi.com/weather/64x64/night/143.png",
      "code": 1030
    },
    "wind_mph": 3.4,
    "wind_kph": 5.4,
    "wind_degree": 293,
    "wind_dir": "WNW",
    "pressure_mb": 1011.0,
    "pressure_in": 29.85,
    "precip_mm": 0.0,
    "precip_in": 0.0,
    "humidity": 65,
    "cloud": 0,
    "feelslike_c": 27.4,
    "feelslike_f": 81.3,
    "windchill_c": 25.9,
    "windchill_f": 78.7,
    "heatindex_c": 27.0,
    "heatindex_f": 80.6,
    "dewpoint_c": 17.0,
    "dewpoint_f": 62.6,
    "vis_km": 3.0,
    "vis_miles": 1.0,
    "uv": 0.0,
    "gust_mph": 4.9,
    "gust_kph": 7.9
  }
}