{
  "location": {
    "name": "Mumbai",
    "region": "Maharashtra",
    "country": "India",
    "lat": 18.975,
    "lon": 72.826,
    "tz_id": "Asia/Kolkata",
    "localtime_epoch": 1775209268,
    "localtime": "2026-04-03 15:11"
  },
  "current": {
    "last_updated_epoch": 1775208600,
    "last_updated": "2026-04-03 15:00",
    "temp_c": 31.1,
    "temp_f": 88.0,
    "is_day": 1,
    "condition": {
      "text": "Overcast",
      "icon": "//cdn.weatherapi.com/weather/64x64/day/122.png",
      "code": 1009
    },
    "wind_mph": 13.9,
    "wind_kph": 22.3,
    "wind_degree": 274,
    "wind_dir": "W",
    "pressure_mb": 1010.0,
    "pressure_in": 29.83,
    "precip_mm": 0.0,
    "precip_in": 0.0,
    "humidity": 59,
    "cloud": 25,
    "feelslike_c": 36.2,
    "feelslike_f": 97.2,
    "windchill_c": 27.7,
    "windchill_f": 81.9,
    "heatindex_c": 29.8,
    "heatindex_f": 85.6,
    "dewpoint_c": 20.4,
    "dewpoint_f": 68.7,
    "vis_km": 4.5,
    "vis_miles": 2.0,
    "uv": 4.7,
    "gust_mph": 18.1,
    "gust_kph": 29.2
  }
}