{
  "location": {
    "name": "Mumbai",
    "region": "Maharashtra",
    "country": "India",
    "lat": 18.975,
    "lon": 72.826,
    "tz_id": "Asia/Kolkata",
    "localtime_epoch": 1775402412,
    "localtime": "2026-04-05 20:50"
  },
  "current": {
    "last_updated_epoch": 1775402100,
    "last_updated": "2026-04-05 20:45",
    "temp_c": 27.3,
    "temp_f": 81.1,
    "is_day": 0,
    "condition": {
      "text": "Overcast",
      "icon": "//cdn.weatherapi.com/weather/64x64/night/122.png",
      "code": 1009
    },
    "wind_mph": 9.6,
    "wind_kph": 15.5,
    "wind_degree": 280,
    "wind_dir": "W",
    "pressure_mb": 1011.0,
    "pressure_in": 29.85,
    "precip_mm": 0.0,
    "precip_in": 0.0,
    "humidity": 58,
    "cloud": 25,
    "feelslike_c": 28.6,
    "feelslike_f": 83.5,
    "windchill_c": 26.7,
    "windchill_f": 80.1,
    "heatindex_c": 27.9,
    "heatindex_f": 82.2,
    "dewpoint_c": 17.9,
    "dewpoint_f": 64.2,
    "vis_km": 5.0,
    "vis_miles": 3.0,
    "uv": 0.0,
    "gust_mph": 13.5,
    "gust_kph": 21.7
  }
}