{
  "location": {
    "name": "Mumbai",
    "region": "Maharashtra",
    "country": "India",
    "lat": 18.975,
    "lon": 72.826,
    "tz_id": "Asia/Kolkata",
    "localtime_epoch": 1772206005,
    "localtime": "2026-02-27 20:56"
  },
  "current": {
    "last_updated_epoch": 1772205300,
    "last_updated": "2026-02-27 20:45",
    "temp_c": 26.4,
    "temp_f": 79.5,
    "is_day": 0,
    "condition": {
      "text": "Overcast",
      "icon": "//cdn.weatherapi.com/weather/64x64/night/122.png",
      "code": 1009
    },
    "wind_mph": 6.0,
    "wind_kph": 9.7,
    "wind_degree": 288,
    "wind_dir": "WNW",
    "pressure_mb": 1010.0,
    "pressure_in": 29.83,
    "precip_mm": 0.0,
    "precip_in": 0.0,
    "humidity": 61,
    "cloud": 25,
    "feelslike_c": 27.6,
    "feelslike_f": 81.8,
    "windchill_c": 25.0,
    "windchill_f": 77.0,
    "heatindex_c": 26.2,
    "heatindex_f": 79.2,
    "dewpoint_c": 16.7,
    "dewpoint_f": 62.1,
    "vis_km": 4.0,
    "vis_miles": 2.0,
    "uv": 0.0,
    "gust_mph": 8.7,
    "gust_kph": 14.0
  }
}