{
  "location": {
    "name": "Pune",
    "region": "Maharashtra",
    "country": "India",
    "lat": 18.5333,
    "lon": 73.8667,
    "tz_id": "Asia/Kolkata",
    "localtime_epoch": 1783691230,
    "localtime": "2026-07-10 19:17"
  },
  "current": {
    "last_updated_epoch": 1783690200,
    "last_updated": "2026-07-10 19:00",
    "temp_c": 24.3,
    "temp_f": 75.7,
    "is_day": 1,
    "condition": {
      "text": "Patchy rain nearby",
      "icon": "//cdn.weatherapi.com/weather/64x64/day/176.png",
      "code": 1063
    },
    "wind_mph": 12.8,
    "wind_kph": 20.5,
    "wind_degree": 256,
    "wind_dir": "WSW",
    "pressure_mb": 1010.0,
    "pressure_in": 29.81,
    "precip_mm": 0.01,
    "precip_in": 0.0,
    "humidity": 83,
    "cloud": 85,
    "feelslike_c": 16.3,
    "feelslike_f": 61.3,
    "windchill_c": 24.3,
    "windchill_f": 75.7,
    "heatindex_c": 26.3,
    "heatindex_f": 79.4,
    "dewpoint_c": 21.2,
    "dewpoint_f": 70.1,
    "vis_km": 10.0,
    "vis_miles": 6.0,
    "uv": 0.0,
    "gust_mph": 16.4,
    "gust_kph": 26.3,
    "will_it_rain": 0,
    "chance_of_rain": 23,
    "will_it_snow": 0,
    "chance_of_snow": 0
  }
}