{
  "location": {
    "name": "Pune",
    "region": "Maharashtra",
    "country": "India",
    "lat": 18.5333,
    "lon": 73.8667,
    "tz_id": "Asia/Kolkata",
    "localtime_epoch": 1763036254,
    "localtime": "2025-11-13 17:47"
  },
  "current": {
    "last_updated_epoch": 1763036100,
    "last_updated": "2025-11-13 17:45",
    "temp_c": 24.6,
    "temp_f": 76.3,
    "is_day": 1,
    "condition": {
      "text": "Sunny",
      "icon": "//cdn.weatherapi.com/weather/64x64/day/113.png",
      "code": 1000
    },
    "wind_mph": 2.7,
    "wind_kph": 4.3,
    "wind_degree": 40,
    "wind_dir": "NE",
    "pressure_mb": 1013.0,
    "pressure_in": 29.93,
    "precip_mm": 0.0,
    "precip_in": 0.0,
    "humidity": 42,
    "cloud": 2,
    "feelslike_c": 25.2,
    "feelslike_f": 77.4,
    "windchill_c": 24.6,
    "windchill_f": 76.3,
    "heatindex_c": 25.2,
    "heatindex_f": 77.4,
    "dewpoint_c": 11.0,
    "dewpoint_f": 51.8,
    "vis_km": 10.0,
    "vis_miles": 6.0,
    "uv": 0.2,
    "gust_mph": 5.0,
    "gust_kph": 8.1,
    "short_rad": 600.8,
    "diff_rad": 93.98,
    "dni": 643.26,
    "gti": 454.17
  }
}